[
  {
    "序号": 0,
    "名称": "愚者 (The Fool)",
    "牌面描述": "一位身着华丽斑斓服饰的年轻人在悬崖边缘阔步向前，他抬头仰望天空，对眼前的悬崖浑然不觉。他右手持一朵白玫瑰象征纯洁，左手用手杖挑着一个小包袱。脚边有一只白色小狗，似乎在提醒他危险，又像在与他同乐。",
    "正位喻意": "新的开始、无限的可能、自发性、盲目的乐观、跟随内心的直觉、踏上未知的新旅程、不拘一格、纯真。",
    "逆位喻意": "鲁莽、过度冒险、不计后果、错失良机、天真导致的受挫、缺乏计划、在关键时刻退缩或行事乖张。"
  },
  {
    "序号": 1,
    "名称": "魔术师 (The Magician)",
    "牌面描述": "魔术师身穿红袍与白内搭，高举右手指向天空，左手指向大地，象征“如其在上，如其在下”。他面前的桌子上摆放着星币、圣杯、宝剑和权杖，代表四大元素。头顶有无限符号（∞）。",
    "正位喻意": "创造力、行动力、显化愿望的能力、自信、专注、沟通能力强、掌握资源并能熟练运用、拥有无限潜能。",
    "逆位喻意": "操纵、欺骗、能力未发挥、缺乏自信、计划不周、才华被滥用、沟通不良、意志力薄弱。"
  },
  {
    "序号": 2,
    "名称": "女祭司 (The High Priestess)",
    "牌面描述": "女祭司端坐于两根柱子（黑色的B和白色的J）之间，身后是画满棕榈叶和石榴的帷幕。她身穿蓝色长袍，怀抱一卷刻有“TORA”字样的卷轴，脚踏一弯新月。",
    "正位喻意": "直觉、潜意识、神秘、内在的智慧、静默、被动、洞察力、顺应自然规律、倾听内心的声音。",
    "逆位喻意": "忽视直觉、隐藏的秘密被揭露、表面化、缺乏内省、情绪化、冷漠、压抑内心的真实感受。"
  },
  {
    "序号": 3,
    "名称": "皇后 (The Empress)",
    "牌面描述": "一位丰满美丽的女性头戴十二星冠冕，身穿印有石榴图案的宽松长裙，舒适地坐在铺满天鹅绒的宝座上。周围是茂盛的森林、麦田和流淌的瀑布，宝座旁有一个代表金星的盾牌。",
    "正位喻意": "丰收、母性、创造力、繁荣、孕育、自然的美与享受、充沛的情感、生活富足、充满关爱与温暖。",
    "逆位喻意": "过度溺爱、缺乏创造力、停滞不前、依赖性过强、物质匮乏、情感上的空虚或控制欲过强。"
  },
  {
    "序号": 4,
    "名称": "皇帝 (The Emperor)",
    "牌面描述": "一位威严的长者头戴皇冠，身穿红色长袍与铠甲，端坐在雕有公羊头（白羊座象征）的石座上。他右手持代表生命的十字权杖，左手持代表世界的宝球，背景是坚硬的岩山。",
    "正位喻意": "权威、结构、逻辑、父亲形象、秩序、领导力、建立规则、坚如磐石的稳定、保护者、强烈的意志力。",
    "逆位喻意": "独裁、暴政、固执己见、滥用权力、缺乏纪律、秩序混乱、过于刻板、不负责任的领导者。"
  },
  {
    "序号": 5,
    "名称": "教皇 (The Hierophant)",
    "牌面描述": "教皇头戴三重冠，身穿红袍，端坐于两根石柱之间。他右手结出祝福的手印，左手持有三重十字架。两位信徒跪在他面前，地上交叉放着两把金银钥匙。",
    "正位喻意": "传统、信仰、教育、精神指引、遵循社会规范、体制内的运作、寻求专业建议、仪式感、正统观念。",
    "逆位喻意": "盲目服从、打破传统、挑战权威、思想僵化、不合常规的做法、虚伪、教条主义、摆脱束缚。"
  },
  {
    "序号": 6,
    "名称": "恋人 (The Lovers)",
    "牌面描述": "亚当和夏娃赤裸着站在伊甸园中，夏娃背后是带有蛇的智慧树，亚当背后是生命树。天使大天使拉斐尔在他们上方张开双翼，太阳在天使头顶高高升起。",
    "正位喻意": "爱情、和谐、亲密关系、价值观的契合、重要的选择、结合、吸引力、纯洁的伴侣关系。",
    "逆位喻意": "感情不和、糟糕的选择、价值观冲突、失去平衡、诱惑、不信任、关系破裂、逃避责任。"
  },
  {
    "序号": 7,
    "名称": "战车 (The Chariot)",
    "牌面描述": "一位全副武装的勇士站在由一黑一白两只狮身人面兽拉着的战车上，战车上方是星辰帷幕。勇士手持魔杖，表情坚定，背对背后的城市，即将踏上征程。",
    "正位喻意": "意志力、胜利、克服困难、掌控局势、自我约束、坚定的决心、旅行、冲突中的平衡、取得世俗成就。",
    "逆位喻意": "失控、缺乏方向、挫折、内心的冲突、好胜心过强导致失败、计划受阻、被情绪或欲望左右。"
  },
  {
    "序号": 8,
    "名称": "力量 (Strength)",
    "牌面描述": "一位身穿白袍的女性温柔而坚定地抚摸着一头狮子的头部和下巴，狮子在她手下显得温顺。女性头顶有无限符号（∞），背景是生机勃勃的自然风光。",
    "正位喻意": "内在的勇气、耐心、同情心、柔克刚、驯服野性、宽容、自信但不张扬、坚韧不拔的意志。",
    "逆位喻意": "自我怀疑、软弱、失去耐心、情绪失控、被本能或欲望支配、恐惧、缺乏自信、力量滥用。"
  },
  {
    "序号": 9,
    "名称": "隐士 (The Hermit)",
    "牌面描述": "一位身穿灰色长袍的老者独自站在冰天雪地的山顶上。他右手高举一盏提灯，灯内闪烁着六芒星的光芒，左手拄着一根长长的手杖。",
    "正位喻意": "内省、孤独、寻求灵魂指引、沉思、寻求内在真理、退隐、独处带来的智慧、指路明灯、谨慎。",
    "逆位喻意": "孤僻、过度封闭、拒绝外界帮助、迷失方向、逃避现实、感到被孤立、偏执、错失社交机会。"
  },
  {
    "序号": 10,
    "名称": "命运之轮 (Wheel of Fortune)",
    "牌面描述": "画面中央是一个悬浮在天空中的巨大轮子，轮盘上刻有代表神圣名字的字母。轮子周围有阿努比斯、蛇和狮身人面像。四个角落分别是代表四大元素的带翼活物（人、鹰、狮、牛），正在阅读书籍。",
    "正位喻意": "命运的转折、好运、机遇、周期的变化、因果循环、无法预料的积极改变、命中注定的事件。",
    "逆位喻意": "厄运、阻力、事情失控、陷入困境、拒绝改变、重复过去的错误、运气不佳、低谷期。"
  },
  {
    "序号": 11,
    "名称": "正义 (Justice)",
    "牌面描述": "正义女神端坐在紫色帷幕前，右手高举一把双刃剑，象征理性和决断；左手提着天平，象征平衡与公平。她身披红袍，头戴镶有宝石的金冠。",
    "正位喻意": "公平、客观、法律、因果报应、诚实、平衡、做出理性的决定、为自己的行为负责、真相大白。",
    "逆位喻意": "不公、偏见、不诚实、逃避责任、法律纠纷失利、优柔寡断、带有偏见的判断、道德缺失。"
  },
  {
    "序号": 12,
    "名称": "倒吊人 (The Hanged Man)",
    "牌面描述": "一名男子被倒吊在一棵呈T字形的树上，他的右腿被绑住，左腿交叉在后。他的双手背在身后，但表情并不痛苦，反而安详，头顶环绕着智慧的光环。",
    "正位喻意": "牺牲、换位思考、暂停、顺其自然、通过放弃获得新视角、内心的顿悟、自愿的等待。",
    "逆位喻意": "无谓的牺牲、钻牛角尖、抗拒改变、错失良机、徒劳无功、自我束缚、缺乏奉献精神。"
  },
  {
    "序号": 13,
    "名称": "死神 (Death)",
    "牌面描述": "一具身穿黑色铠甲的骷髅骑在白马上，手持一面印有白色玫瑰的黑色旗帜。在他马下，国王已经倒下，主教在祈祷，小孩和妇女在求饶。背景中，一轮太阳正在两座塔之间升起（或落下）。",
    "正位喻意": "结束与新生、巨大的转变、除旧布新、放手、必然的改变、告别过去、精神或生活上的重生。",
    "逆位喻意": "抗拒改变、停滞不前、无法放手、恐惧未知、处于痛苦的边缘却不愿改变、拖延、深陷旧习。"
  },
  {
    "序号": 14,
    "名称": "节制 (Temperance)",
    "牌面描述": "一位天使一脚踏在水中，一脚踏在岸上。他双手各持一个圣杯，正在将水从一个杯子倒入另一个杯子，水流在半空中奇妙地倾斜流动。天使额头有太阳符号，胸前有代表物质与精神的正方形与三角形。",
    "正位喻意": "平衡、中庸、调和、耐心、自我控制、疗愈、将不同的事物融合产生良好的结果、平稳的发展。",
    "逆位喻意": "失衡、极端、缺乏耐心、过度放纵、冲突、无法融合、精力分散、做事急躁。"
  },
  {
    "序号": 15,
    "名称": "恶魔 (The Devil)",
    "牌面描述": "一个长着蝙蝠翅膀、羊角和兽腿的恶魔蹲在黑色的石座上。石座下用铁链锁着一对赤裸的男女（类似恋人牌中的亚当夏娃），但铁链很松，他们随时可以挣脱，却似乎并未察觉。",
    "正位喻意": "束缚、沉迷物质、上瘾、诱惑、执念、被负面情绪控制、限制性信念、性欲与肉体的欲望。",
    "逆位喻意": "解脱、打破束缚、克服上瘾、重获自由、看穿假象、重拾精神力量、拒绝诱惑。"
  },
  {
    "序号": 16,
    "名称": "高塔 (The Tower)",
    "牌面描述": "一座建在高山上的孤塔被闪电击中，塔顶的王冠被击落，塔身燃起熊熊烈火。一男一女从塔中坠落，背景是黑暗的天空和纷飞的火花。",
    "正位喻意": "突如其来的灾难、彻底的破坏、信念的崩塌、意外的巨变、解除虚假的幻象、动荡、必须面对的残酷真相。",
    "逆位喻意": "避免了更坏的结果、悬而未决的恐惧、抗拒必要的改变、拖延危机、内心的崩溃但表面强撑。"
  },
  {
    "序号": 17,
    "名称": "星星 (The Star)",
    "牌面描述": "在繁星点点的夜空下，一位赤裸的女子跪在水池边。她双手各持一个水壶，一壶水倒入池中，激起涟漪；一壶水倒在草地上，化作五道水流。天空中有一颗巨大的八芒星和七颗小星。",
    "正位喻意": "希望、灵感、宁静、疗愈、对未来的憧憬、好运、清晰的愿景、精神上的指引、恢复活力。",
    "逆位喻意": "绝望、缺乏信心、失去灵感、悲观、目标不切实际、自我怀疑、错过好机会。"
  },
  {
    "序号": 18,
    "名称": "月亮 (The Moon)",
    "牌面描述": "一轮悬挂在夜空的明月（同时具有满月、新月和人脸的特征）。下方有一只狗和一匹狼对着月亮吠叫，代表驯化与野性的本能。水池中有一只小龙虾正在爬向陆地上的小路，小路蜿蜒通向远方的两座塔。",
    "正位喻意": "不安、幻觉、潜意识的恐惧、未知、迷惑、隐藏的敌人、直觉、难以看清真相、情绪波动。",
    "逆位喻意": "恐惧消散、看清真相、摆脱迷惑、揭露秘密、解除误会、直面内心的阴暗面、豁然开朗。"
  },
  {
    "序号": 19,
    "名称": "太阳 (The Sun)",
    "牌面描述": "一轮巨大的太阳在天空中发出耀眼的光芒，照亮了整个画面。下方有一个赤裸的孩童骑在白马上，孩童头上戴着花环，插着一根红羽毛，手中挥舞着红色的旗帜，背后是向日葵和一堵砖墙。",
    "正位喻意": "快乐、成功、活力、真相大白、积极乐观、充满生命力、丰收、喜庆、事业或爱情上的圆满。",
    "逆位喻意": "暂时的挫折、快乐被打折、过度乐观、缺乏热情、自我膨胀、成功延迟、需要更多的努力。"
  },
  {
    "序号": 20,
    "名称": "审判 (Judgement)",
    "牌面描述": "大天使加百列在天空中吹响号角，号角上挂着带有红十字的白旗。下方的大地裂开，男人、女人和孩子从棺木中站起，张开双臂迎接天使的呼唤，背景是广阔的海洋和雪山。",
    "正位喻意": "觉醒、重生、反省、因果决断、听到内心的呼唤、原谅与救赎、重大的决定、人生的新阶段。",
    "逆位喻意": "缺乏自我反省、拒绝改变、逃避结果、自我怀疑、错过重生机会、固步自封、深陷悔恨之中。"
  },
  {
    "序号": 21,
    "名称": "世界 (The World)",
    "牌面描述": "一位赤裸的女性（或双性人）披着紫色的绸带，在由绿色月桂叶编织成的巨大花环中翩翩起舞，她双手各持一根魔杖。花环的四个角落再次出现了代表四大元素的带翼活物（人、鹰、狮、牛）。",
    "正位喻意": "圆满、达成目标、成功、整体性、旅行、完美的结局、身心合一、到达巅峰、进入新的循环。",
    "逆位喻意": "未完成、缺乏进展、未能圆满、停滞在最后一步、眼界狭隘、无法释怀、推迟的成功。"
  }
]